lipydomics/__init__.py
lipydomics/data.py
lipydomics/interactive.py
lipydomics/plotting.py
lipydomics/stats.py
lipydomics/util.py
lipydomics/identification/__init__.py
lipydomics/identification/build_database.py
lipydomics/identification/build_params.py
lipydomics/identification/characterize_lipid_ccs_pred.py
lipydomics/identification/characterize_lipid_rt_pred.py
lipydomics/identification/db_table_defs.py
lipydomics/identification/encoder_params.py
lipydomics/identification/fill_measured_from_src.py
lipydomics/identification/fill_theo_mz_from_gen.py
lipydomics/identification/id_levels.py
lipydomics/identification/lipid_ccs_pred.pickle
lipydomics/identification/lipid_ccs_scale.pickle
lipydomics/identification/lipid_rt_pred.pickle
lipydomics/identification/lipid_rt_scale.pickle
lipydomics/identification/lipids.db
lipydomics/identification/mz_generation.py
lipydomics/identification/rt_calibration.py
lipydomics/identification/train_lipid_ccs_pred.py
lipydomics/identification/train_lipid_rt_pred.py
lipydomics/identification/LipidMass/__init__.py
lipydomics/identification/LipidMass/base.py
lipydomics/identification/LipidMass/monoiso.py
lipydomics/identification/LipidMass/lipids/__init__.py
lipydomics/identification/LipidMass/lipids/glycerolipids.py
lipydomics/identification/LipidMass/lipids/glycerophospholipids.py
lipydomics/identification/LipidMass/lipids/glycolipids.py
lipydomics/identification/LipidMass/lipids/lysoglycerophospholipids.py
lipydomics/identification/LipidMass/lipids/misc.py
lipydomics/identification/LipidMass/lipids/sphingolipids/__init__.py
lipydomics/identification/LipidMass/lipids/sphingolipids/gangliosides.py
lipydomics/identification/builds/build_log_2108240850.txt
lipydomics/identification/builds/lipids_2108240850.db
lipydomics/identification/ccs_pred_perf/100_FA_[M-H]-.png
lipydomics/identification/ccs_pred_perf/10_Cer_[M+H-H2O]+.png
lipydomics/identification/ccs_pred_perf/10_Cer_[M+HCOO]-.png
LiPydomics-1.6.8.dist-info/LICENSE
LiPydomics-1.6.8.dist-info/METADATA
LiPydomics-1.6.8.dist-info/WHEEL
LiPydomics-1.6.8.dist-info/top_level.txt
LiPydomics-1.6.8.dist-info/zip-safe
LiPydomics-1.6.8.dist-info/RECORD
