Metadata-Version: 2.1
Name: LiPydomics
Version: 1.6.8
Summary: a library for streamlining lipidomics data analysis.
Home-page: https://github.com/dylanhross/lipydomics
Author: Dylan H. Ross
Author-email: "Dylan H. Ross" <dhross92@uw.edu>
Maintainer-email: Noelle Reimers <nreimers@uw.edu>
License: MIT
Project-URL: Homepage, https://github.com/dylanhross/lipydomics
Project-URL: Bug Tracker, https://github.com/dylanhross/lipydomics/issues
Classifier: Programming Language :: Python :: 3
Classifier: License :: OSI Approved :: MIT License
Classifier: Operating System :: OS Independent
Requires-Python: >=3.8
License-File: LICENSE
Requires-Dist: matplotlib (>=3.1.3)
Requires-Dist: numpy (>=1.18.1)
Requires-Dist: pandas (>=1.0.1)
Requires-Dist: scikit-learn (>=0.24.1)
Requires-Dist: scipy (>=1.4.1)
